pipowl/__init__.py
pipowl/cli.py
pipowl/core.py
pipowl/utils.py
pipowl/version.py
pipowl/lang/__init__.py
pipowl/lang/lang.py
pipowl/semantic/__init__.py
pipowl/semantic/semantic.py
pipowl-1.6.0.dist-info/licenses/Licence
pipowl-1.6.0.dist-info/METADATA
pipowl-1.6.0.dist-info/WHEEL
pipowl-1.6.0.dist-info/entry_points.txt
pipowl-1.6.0.dist-info/top_level.txt
pipowl-1.6.0.dist-info/RECORD
