Metadata-Version: 2.4
Name: pipowl
Version: 1.6.0
Summary: SemanticOwl + LangOwl open-core
Author-email: SadlyOwl <galaxy455238@gmail.com>
License-Expression: MIT
Project-URL: Homepage, https://github.com/galaxy4552/pipowl
Keywords: owl,ai,local,tooling
Requires-Python: >=3.8
License-File: Licence
Requires-Dist: numpy
Requires-Dist: sentence-transformers
Dynamic: license-file
